cellfree/__init__.py
cellfree/cellfree.py
cellfree-0.0.1.dist-info/LICENSE
cellfree-0.0.1.dist-info/WHEEL
cellfree-0.0.1.dist-info/METADATA
cellfree-0.0.1.dist-info/RECORD
