Metadata-Version: 2.1
Name: cellfree
Version: 0.0.1
Summary: A cell free DNA analysis suite
Home-page: https://github.com/zztin/cellfree
License: GNU General Public License v3
Author: Liting Chen
Author-email: litingchen16@gmail.com
Requires-Python: >=3.8,<4.0
Classifier: License :: Other/Proprietary License
Classifier: Programming Language :: Python :: 3
Classifier: Programming Language :: Python :: 3.10
Classifier: Programming Language :: Python :: 3.8
Classifier: Programming Language :: Python :: 3.9
Requires-Dist: matplotlib (>=3.5.1,<4.0.0)
Project-URL: Repository, https://github.com/zztin/cellfree
